extended/__init__.py
extended/classes.py
extended/comprehensions.py
extended/indexing.py
extended/iterable.py
extended/main.py
extended/nesting.py
extended/numbertests.py
extended/tests.py
extended/version.py
extended-0.0.8.dist-info/LICENSE.txt
extended-0.0.8.dist-info/METADATA
extended-0.0.8.dist-info/WHEEL
extended-0.0.8.dist-info/top_level.txt
extended-0.0.8.dist-info/RECORD
