Metadata-Version: 1.0
Name: extended
Version: 0.0.8
Summary: python implementations of a number of wolfram language functions
Home-page: https://github.com/NGeorgescu/wolframtools
Author: NGeorgescu
Author-email: nsgeorgescu@gmail.com
License: see LICENSE.txt
Keywords: wolfram mathematica python ports wolframalpha
Platform: UNKNOWN
